geopak/__init__.py
geopak/common.py
geopak/geopak.py
geopak/utils.py
geopak-0.0.3.dist-info/LICENSE
geopak-0.0.3.dist-info/METADATA
geopak-0.0.3.dist-info/WHEEL
geopak-0.0.3.dist-info/entry_points.txt
geopak-0.0.3.dist-info/top_level.txt
geopak-0.0.3.dist-info/RECORD
