Metadata-Version: 2.1
Name: geopak
Version: 0.0.3
Summary: python package demo for geodpatial analysis
Author-email: Albert Tandoh <atandoh004@St.ug.edu.gh>
License: MIT License
Project-URL: Homepage, https://github.com/Tandoh004/geopak
Keywords: geopak
Classifier: Intended Audience :: Developers
Classifier: License :: OSI Approved :: MIT License
Classifier: Natural Language :: English
Classifier: Programming Language :: Python :: 3.8
Classifier: Programming Language :: Python :: 3.9
Classifier: Programming Language :: Python :: 3.10
Classifier: Programming Language :: Python :: 3.11
Classifier: Programming Language :: Python :: 3.12
Requires-Python: >=3.8
License-File: LICENSE
Requires-Dist: numpy
Requires-Dist: ipyleaflet
Requires-Dist: pandas
Provides-Extra: all
Requires-Dist: geopak[extra] ; extra == 'all'
Provides-Extra: extra
Requires-Dist: pandas ; extra == 'extra'
